streamlit_text_annotation/__init__.py
streamlit_text_annotation/frontend/dist/index.html
streamlit_text_annotation/frontend/dist/css/app.16a5b519.css
streamlit_text_annotation/frontend/dist/js/app.67272d70.js
streamlit_text_annotation/frontend/dist/js/app.67272d70.js.map
streamlit_text_annotation/frontend/dist/js/chunk-vendors.7e673700.js
streamlit_text_annotation/frontend/dist/js/chunk-vendors.7e673700.js.map
streamlit_text_annotation-0.1.5.dist-info/LICENSE
streamlit_text_annotation-0.1.5.dist-info/METADATA
streamlit_text_annotation-0.1.5.dist-info/WHEEL
streamlit_text_annotation-0.1.5.dist-info/top_level.txt
streamlit_text_annotation-0.1.5.dist-info/RECORD
