Metadata-Version: 2.1
Name: streamlit-text-annotation
Version: 0.1.5
Summary: streamlit-text-annotation is a simple streamlit component for displaying and editing text annotations.
Home-page: https://github.com/victoryhb/streamlit-text-annotation
Author: Victor Yan
Author-email: victoryhb@163.com
License: UNKNOWN
Platform: UNKNOWN
Requires-Python: >=3.6
License-File: LICENSE
Requires-Dist: streamlit (>=0.63)
